fastrpc/__init__.py
fastrpc/file_handler.py
fastrpc/todo.py
fastrpc-1.0.16.dist-info/DESCRIPTION.rst
fastrpc-1.0.16.dist-info/METADATA
fastrpc-1.0.16.dist-info/RECORD
fastrpc-1.0.16.dist-info/WHEEL
fastrpc-1.0.16.dist-info/entry_points.txt
fastrpc-1.0.16.dist-info/metadata.json
fastrpc-1.0.16.dist-info/top_level.txt
page/__init__.py
page/file_handler.py
page/todo.py
pytodos/__init__.py
pytodos/file_handler.py
pytodos/todo.py
